{
  "video": "xl3",
  "frame": "xl3_00109.jpg",
  "scores": {
    "detection_0": {
      "drainage_effect": 3.88,
      "distribution_state": 3.6,
      "action": 4.06,
      "thickness": 4.0,
      "cleanliness": 3.06,
      "elasticity": 3.49,
      "ripeness": 3.0,
      "operation_standardization": 3.94,
      "position": 4.38,
      "tool_coordination": 4.0,
      "soup_adhesion": 3.6,
      "noodle_soup_ratio": 3.6,
      "integrity": 3.49,
      "coordination": 3.94,
      "notes": "关键帧时间线性插值"
    }
  },
  "stage": "boiling_scooping",
  "interpolated": true
}