{
  "video": "xl3",
  "frame": "xl3_00146.jpg",
  "scores": {
    "detection_0": {
      "thickness": 4,
      "elasticity": 4,
      "integrity": 4,
      "ripeness": 3,
      "notes": ""
    },
    "detection_1": {
      "position": 4,
      "action": 4,
      "coordination": 3,
      "tool_coordination": 5,
      "notes": ""
    },
    "detection_2": {
      "operation_standardization": 3,
      "cleanliness": 3,
      "drainage_effect": 3,
      "notes": ""
    }
  },
  "stage": "boiling_scooping",
  "timestamp": 1770691624.4664478
}